get_prime_number/__init__.py
get_prime_number-0.1.dist-info/LICENSE
get_prime_number-0.1.dist-info/METADATA
get_prime_number-0.1.dist-info/WHEEL
get_prime_number-0.1.dist-info/top_level.txt
get_prime_number-0.1.dist-info/RECORD
