Metadata-Version: 2.1
Name: get-prime-number
Version: 0.1
Summary: A prime number generator
Home-page: https://github.com/naijopkr/get-prime-number
Author: Ariel Barcellos
Author-email: contact@arielbarcellos.com
License: UNKNOWN
Platform: UNKNOWN
Classifier: Programming Language :: Python :: 3
Classifier: Operating System :: OS Independent
Requires-Python: >=3.0
